breezy-3.3.13.data/scripts/bzr-upload-pack
breezy-3.3.13.data/scripts/git-remote-bzr
breezy-3.3.13.data/scripts/bzr-receive-pack
breezy-3.3.13.data/data/share/locale/sk/LC_MESSAGES/breezy.mo
breezy-3.3.13.data/data/share/locale/ug/LC_MESSAGES/breezy.mo
breezy-3.3.13.data/data/share/locale/pl/LC_MESSAGES/breezy.mo
breezy-3.3.13.data/data/share/locale/vi/LC_MESSAGES/breezy.mo
breezy-3.3.13.data/data/share/locale/sv/LC_MESSAGES/breezy.mo
breezy-3.3.13.data/data/share/locale/he/LC_MESSAGES/breezy.mo
breezy-3.3.13.data/data/share/locale/ms/LC_MESSAGES/breezy.mo
breezy-3.3.13.data/data/share/locale/pt_BR/LC_MESSAGES/breezy.mo
breezy-3.3.13.data/data/share/locale/ja/LC_MESSAGES/breezy.mo
breezy-3.3.13.data/data/share/locale/el/LC_MESSAGES/breezy.mo
breezy-3.3.13.data/data/share/locale/sco/LC_MESSAGES/breezy.mo
breezy-3.3.13.data/data/share/locale/oc/LC_MESSAGES/breezy.mo
breezy-3.3.13.data/data/share/locale/it/LC_MESSAGES/breezy.mo
breezy-3.3.13.data/data/share/locale/ca/LC_MESSAGES/breezy.mo
breezy-3.3.13.data/data/share/locale/cs/LC_MESSAGES/breezy.mo
breezy-3.3.13.data/data/share/locale/ru/LC_MESSAGES/breezy.mo
breezy-3.3.13.data/data/share/locale/ro/LC_MESSAGES/breezy.mo
breezy-3.3.13.data/data/share/locale/zh_CN/LC_MESSAGES/breezy.mo
breezy-3.3.13.data/data/share/locale/ckb/LC_MESSAGES/breezy.mo
breezy-3.3.13.data/data/share/locale/pt/LC_MESSAGES/breezy.mo
breezy-3.3.13.data/data/share/locale/uk/LC_MESSAGES/breezy.mo
breezy-3.3.13.data/data/share/locale/sr/LC_MESSAGES/breezy.mo
breezy-3.3.13.data/data/share/locale/en_AU/LC_MESSAGES/breezy.mo
breezy-3.3.13.data/data/share/locale/en_GB/LC_MESSAGES/breezy.mo
breezy-3.3.13.data/data/share/locale/si/LC_MESSAGES/breezy.mo
breezy-3.3.13.data/data/share/locale/ku/LC_MESSAGES/breezy.mo
breezy-3.3.13.data/data/share/locale/bs/LC_MESSAGES/breezy.mo
breezy-3.3.13.data/data/share/locale/my/LC_MESSAGES/breezy.mo
breezy-3.3.13.data/data/share/locale/ar/LC_MESSAGES/breezy.mo
breezy-3.3.13.dist-info/RECORD
breezy-3.3.13.dist-info/WHEEL
breezy-3.3.13.dist-info/entry_points.txt
breezy-3.3.13.dist-info/top_level.txt
breezy-3.3.13.dist-info/METADATA
breezy-3.3.13.dist-info/licenses/COPYING.txt
