Metadata-Version: 2.4
Name: breezy
Version: 3.3.13
Summary: Friendly distributed version control system
Maintainer-email: Breezy Developers <team@breezy-vcs.org>
License-Expression: GPL-2.0-or-later
Project-URL: Homepage, https://www.breezy-vcs.org/
Project-URL: Download, https://launchpad.net/brz/+download
Project-URL: Repository, https://github.com/breezy-team/breezy
Classifier: Development Status :: 6 - Mature
Classifier: Environment :: Console
Classifier: Intended Audience :: Developers
Classifier: Intended Audience :: System Administrators
Classifier: Operating System :: OS Independent
Classifier: Operating System :: POSIX
Classifier: Programming Language :: Python
Classifier: Programming Language :: Rust
Classifier: Programming Language :: C
Classifier: Topic :: Software Development :: Version Control
Requires-Python: <3.15,>=3.9
License-File: COPYING.txt
Requires-Dist: configobj
Requires-Dist: fastbencode
Requires-Dist: patiencediff
Requires-Dist: merge3
Requires-Dist: dulwich==0.24.1
Requires-Dist: urllib3>=1.24.1
Requires-Dist: pyyaml
Provides-Extra: fastimport
Requires-Dist: fastimport>=0.9.8; extra == "fastimport"
Provides-Extra: git
Requires-Dist: dulwich>=0.21.6; extra == "git"
Provides-Extra: launchpad
Requires-Dist: launchpadlib>=1.6.3; extra == "launchpad"
Provides-Extra: workspace
Requires-Dist: pyinotify; extra == "workspace"
Requires-Dist: pyasyncore; python_version >= "3.12" and extra == "workspace"
Provides-Extra: doc
Requires-Dist: docutils; extra == "doc"
Requires-Dist: setuptools; extra == "doc"
Requires-Dist: sphinx; extra == "doc"
Requires-Dist: sphinx_epytext; extra == "doc"
Provides-Extra: pgp
Requires-Dist: gpg; extra == "pgp"
Provides-Extra: github
Requires-Dist: github; extra == "github"
Provides-Extra: paramiko
Requires-Dist: paramiko; extra == "paramiko"
Provides-Extra: subunit
Requires-Dist: python-subunit; extra == "subunit"
Provides-Extra: dev
Requires-Dist: testtools; extra == "dev"
Requires-Dist: testscenarios; extra == "dev"
Requires-Dist: python-subunit; extra == "dev"
Requires-Dist: flake8; extra == "dev"
Requires-Dist: cython>=0.29; extra == "dev"
Requires-Dist: ruff; extra == "dev"
Provides-Extra: testing
Requires-Dist: testtools; extra == "testing"
Requires-Dist: testscenarios; extra == "testing"
Requires-Dist: python-subunit; extra == "testing"
Requires-Dist: dulwich>=0.21.6; extra == "testing"
Dynamic: license-file
